Client/__init__.py
Client/auth/__init__.py
Client/auth/credentials_token_provider.py
Client/auth/itoken_provider.py
Client/auth_context.py
Client/constants.py
Client/context.py
Client/context_source.py
Client/engine/__init__.py
Client/engine/engine_factory.py
Client/engine/irps_engine_provider.py
Client/engine/rps_engine.py
Client/engine/rps_engine_converter.py
Client/engine/rps_engine_exception.py
Client/engine_client_options.py
Client/engine_context/__init__.py
Client/engine_context/irps_engine_context_provider.py
Client/engine_context/processing_context.py
Client/engine_context/rights_context.py
Client/engine_context/rps_engine_context_json_file_provider.py
Client/engine_context/rps_engine_context_provider_base.py
Client/engine_context/rps_engine_context_resolver.py
Client/engine_context/rps_engine_context_settings_provider.py
Client/evidence.py
Client/examples/__init__.py
Client/examples/contexts_provided_by_resolver_example.py
Client/examples/simple_usage_example.py
Client/examples/usage_with_dependencies_example.py
Client/examples/usage_with_related_object_example.py
Client/extensions/__init__.py
Client/extensions/context_extensions.py
Client/extensions/json_extensions.py
Client/instance/__init__.py
Client/instance/rps_instance.py
Client/json/__init__.py
Client/json/engine_json_rest_api_client.py
Client/model/__init__.py
Client/model/api/__init__.py
Client/model/api/context/__init__.py
Client/model/api/context/context.py
Client/model/api/context/evidence.py
Client/model/api/error/__init__.py
Client/model/api/error/error.py
Client/model/api/instance.py
Client/model/api/request/__init__.py
Client/model/api/request/request.py
Client/model/api/request/request_body.py
Client/model/api/response/__init__.py
Client/model/api/response/response.py
Client/model/api/response/response_body.py
Client/model/api/rps_value_error.py
Client/model/settings/__init__.py
Client/model/settings/files_settings.py
Client/model/settings/rps_settings.py
rps_engine_client_python-1.0.8.dist-info/METADATA
rps_engine_client_python-1.0.8.dist-info/WHEEL
rps_engine_client_python-1.0.8.dist-info/RECORD
