Metadata-Version: 2.1
Name: rps-engine-client-python
Version: 1.0.8
Summary: Python client library for REGDATA RPS Engine.
License: REGDATA SA
Author: REGDATA SA
Author-email: info@regdata.ch
Requires-Python: >=3.9,<=3.11.9
Classifier: License :: Other/Proprietary License
Classifier: Programming Language :: Python :: 3
Classifier: Programming Language :: Python :: 3.9
Classifier: Programming Language :: Python :: 3.10
Classifier: Programming Language :: Python :: 3.11
Requires-Dist: certifi (==2023.7.22)
Requires-Dist: charset-normalizer (==3.2.0)
Requires-Dist: dependency-injector (==4.41.0)
Requires-Dist: dotenv (>=0.9.9,<0.10.0)
Requires-Dist: idna (==3.4)
Requires-Dist: pydantic (>=2.10.6,<3.0.0)
Requires-Dist: pydantic-settings (>=2.8.1,<3.0.0)
Requires-Dist: python-dotenv (==1.0.0)
Requires-Dist: requests (==2.31.0)
Requires-Dist: six (==1.16.0)
Requires-Dist: urllib3 (==2.0.4)
